raoc/__init__.py
raoc/assets/help-with-chores.jpg
raoc/assets/icon.png
raoc/assets/pick-up-trash.jpg
raoc/assets/visit-elderly-neighbors.jpg
raoc/file_name.py
raoc/main.py
raoc/my_action.py
raoc/perform_action.py
raoc/text_component.py
random_acts_of_kindness-0.2.0.dist-info/METADATA
random_acts_of_kindness-0.2.0.dist-info/WHEEL
random_acts_of_kindness-0.2.0.dist-info/RECORD
